hhconfig.py
hhconfig-1.2.0.dist-info/licenses/LICENSE
hhconfig-1.2.0.dist-info/METADATA
hhconfig-1.2.0.dist-info/WHEEL
hhconfig-1.2.0.dist-info/entry_points.txt
hhconfig-1.2.0.dist-info/top_level.txt
hhconfig-1.2.0.dist-info/RECORD
