Metadata-Version: 2.4
Name: hhconfig
Version: 1.2.0
Summary: Hay Hoist Serial Config Tool
Author-email: Nathan Fraser <ndf-zz@6-v.org>
License-Expression: MIT
Project-URL: homepage, https://github.com/ndf-zz/remootio-adapter/util/hhconfig
Keywords: serial,tk
Classifier: Development Status :: 3 - Alpha
Classifier: Environment :: Win32 (MS Windows)
Classifier: Environment :: X11 Applications
Classifier: Natural Language :: English
Classifier: Operating System :: OS Independent
Classifier: Programming Language :: Python :: 3
Classifier: Topic :: Scientific/Engineering
Requires-Python: >=3.9
License-File: LICENSE
Requires-Dist: pyserial
Dynamic: license-file
